README.md
setup.py
nuplan/__init__.py
nuplan/cli/__init__.py
nuplan/cli/db_cli.py
nuplan/cli/nuplan_cli.py
nuplan/cli/test/__init__.py
nuplan/cli/test/test_nuplan_cli.py
nuplan/common/__init__.py
nuplan/common/actor_state/__init__.py
nuplan/common/actor_state/agent.py
nuplan/common/actor_state/agent_state.py
nuplan/common/actor_state/agent_temporal_state.py
nuplan/common/actor_state/car_footprint.py
nuplan/common/actor_state/dynamic_car_state.py
nuplan/common/actor_state/ego_state.py
nuplan/common/actor_state/ego_temporal_state.py
nuplan/common/actor_state/oriented_box.py
nuplan/common/actor_state/scene_object.py
nuplan/common/actor_state/state_representation.py
nuplan/common/actor_state/static_object.py
nuplan/common/actor_state/tracked_objects.py
nuplan/common/actor_state/tracked_objects_types.py
nuplan/common/actor_state/transform_state.py
nuplan/common/actor_state/vehicle_parameters.py
nuplan/common/actor_state/waypoint.py
nuplan/common/actor_state/test/__init__.py
nuplan/common/actor_state/test/test_actor_temporal_state.py
nuplan/common/actor_state/test/test_agent.py
nuplan/common/actor_state/test/test_car_footprint.py
nuplan/common/actor_state/test/test_dynamic_car_state.py
nuplan/common/actor_state/test/test_ego_state.py
nuplan/common/actor_state/test/test_oriented_box.py
nuplan/common/actor_state/test/test_scene_object.py
nuplan/common/actor_state/test/test_state_representation.py
nuplan/common/actor_state/test/test_tracked_objects.py
nuplan/common/actor_state/test/test_utils.py
nuplan/common/actor_state/test/test_waypoint.py
nuplan/common/geometry/__init__.py
nuplan/common/geometry/compute.py
nuplan/common/geometry/convert.py
nuplan/common/geometry/interpolate_state.py
nuplan/common/geometry/interpolate_tracked_object.py
nuplan/common/geometry/torch_geometry.py
nuplan/common/geometry/transform.py
nuplan/common/geometry/test/__init__.py
nuplan/common/geometry/test/test_compute.py
nuplan/common/geometry/test/test_convert.py
nuplan_devkit.egg-info/PKG-INFO
nuplan_devkit.egg-info/SOURCES.txt
nuplan_devkit.egg-info/dependency_links.txt
nuplan_devkit.egg-info/entry_points.txt
nuplan_devkit.egg-info/top_level.txt